initium/__init__.py
initium/cli.py
initium/generator.py
initium/templates/bioreactor/README.md.tpl
initium/templates/bioreactor/ci_template.yml
initium/templates/bioreactor/config.yml
initium/templates/bioreactor/requirements.txt
initium/templates/bioreactor/control/pid_controller.py
initium/templates/bioreactor/modeling/bioreactor_model.py
initium/templates/bioreactor/simulation/config.py
initium/templates/bioreactor/simulation/main.py
initium/templates/bioreactor/visualization/dashboard.py
initium/templates/hmi/README.md.tpl
initium/templates/plc/README.md.tpl
initium/templates/plc/ci_template.yml
initium/templates/ros/README.md.tpl
initium_fe-0.1.1.dist-info/licenses/LICENSE
initium_fe-0.1.1.dist-info/METADATA
initium_fe-0.1.1.dist-info/WHEEL
initium_fe-0.1.1.dist-info/entry_points.txt
initium_fe-0.1.1.dist-info/top_level.txt
initium_fe-0.1.1.dist-info/RECORD
