Metadata-Version: 2.4
Name: initium-fe
Version: 0.1.1
Summary: Project Bootstrap Tool
Home-page: https://gitlab.com/autowerk/initium
Author: Sahil Jasani
Author-email: jasanisahil11@gmail.com
Classifier: Programming Language :: Python :: 3
Classifier: License :: OSI Approved :: MIT License
Classifier: Operating System :: OS Independent
Requires-Python: >=3.6
License-File: LICENSE
Requires-Dist: requests
Dynamic: author
Dynamic: author-email
Dynamic: classifier
Dynamic: description
Dynamic: description-content-type
Dynamic: home-page
Dynamic: license-file
Dynamic: requires-dist
Dynamic: requires-python
Dynamic: summary
